odoo10_addon_l10n_cn_hr_payroll-10.0.1.0.0-py2.7-nspkg.pth
odoo/addons/l10n_cn_hr_payroll/README.rst
odoo/addons/l10n_cn_hr_payroll/__init__.py
odoo/addons/l10n_cn_hr_payroll/__manifest__.py
odoo/addons/l10n_cn_hr_payroll/data/leave_type_data.xml
odoo/addons/l10n_cn_hr_payroll/data/salary_rule_basic.xml
odoo/addons/l10n_cn_hr_payroll/data/salary_rule_category.xml
odoo/addons/l10n_cn_hr_payroll/data/salary_rule_nj1.xml
odoo/addons/l10n_cn_hr_payroll/data/salary_rule_sh1.xml
odoo/addons/l10n_cn_hr_payroll/data/salary_rule_sh2.xml
odoo/addons/l10n_cn_hr_payroll/data/salary_rule_sh3.xml
odoo/addons/l10n_cn_hr_payroll/data/salary_rule_sh4.xml
odoo/addons/l10n_cn_hr_payroll/data/salary_rule_sz1.xml
odoo/addons/l10n_cn_hr_payroll/data/salary_rule_sz2.xml
odoo/addons/l10n_cn_hr_payroll/data/salary_rule_sz3.xml
odoo/addons/l10n_cn_hr_payroll/data/salary_rule_sz4.xml
odoo/addons/l10n_cn_hr_payroll/i18n/zh_CN.po
odoo/addons/l10n_cn_hr_payroll/models/__init__.py
odoo/addons/l10n_cn_hr_payroll/models/l10n_cn_hr_payroll.py
odoo/addons/l10n_cn_hr_payroll/static/description/icon.png
odoo/addons/l10n_cn_hr_payroll/tests/__init__.py
odoo/addons/l10n_cn_hr_payroll/tests/test_payroll.py
odoo/addons/l10n_cn_hr_payroll/views/l10n_cn_hr_payroll_view.xml
odoo/addons/l10n_cn_hr_payroll/views/report_payslip.xml
odoo10_addon_l10n_cn_hr_payroll-10.0.1.0.0.dist-info/DESCRIPTION.rst
odoo10_addon_l10n_cn_hr_payroll-10.0.1.0.0.dist-info/METADATA
odoo10_addon_l10n_cn_hr_payroll-10.0.1.0.0.dist-info/RECORD
odoo10_addon_l10n_cn_hr_payroll-10.0.1.0.0.dist-info/WHEEL
odoo10_addon_l10n_cn_hr_payroll-10.0.1.0.0.dist-info/metadata.json
odoo10_addon_l10n_cn_hr_payroll-10.0.1.0.0.dist-info/namespace_packages.txt
odoo10_addon_l10n_cn_hr_payroll-10.0.1.0.0.dist-info/top_level.txt
